construct_dataclasses/__init__.py
construct_dataclasses/__init__.pyi
construct_dataclasses/py.typed
construct_dataclasses-1.1.12.dist-info/licenses/LICENSE
construct_dataclasses-1.1.12.dist-info/METADATA
construct_dataclasses-1.1.12.dist-info/WHEEL
construct_dataclasses-1.1.12.dist-info/top_level.txt
construct_dataclasses-1.1.12.dist-info/RECORD
