Metadata-Version: 2.4
Name: construct-dataclasses
Version: 1.1.12
Summary: enhancement for the python package 'construct' that adds support for dataclasses.
Home-page: https://github.com/MatrixEditor/construct-dataclasses
Author: MatrixEditor
License: GNU GPLv3
Keywords: construct,kaitai,declarative,data structure,struct,binary,symmetric,parser,builder,parsing,building,pack,unpack,packer,unpacker,bitstring,bytestring,dataclasses
Platform: POSIX
Platform: Windows
Classifier: Development Status :: 3 - Alpha
Classifier: Intended Audience :: Developers
Classifier: Intended Audience :: Information Technology
Classifier: Operating System :: OS Independent
Classifier: License :: OSI Approved :: GNU General Public License v3 (GPLv3)
Classifier: Programming Language :: Python :: 3.7
Classifier: Programming Language :: Python :: 3.8
Classifier: Programming Language :: Python :: 3.9
Classifier: Programming Language :: Python :: 3.10
Classifier: Programming Language :: Python :: 3.11
Classifier: Programming Language :: Python :: 3.12
Classifier: Programming Language :: Python :: 3.13
Requires-Python: >=3.8
License-File: LICENSE
Requires-Dist: construct
Provides-Extra: dev
Requires-Dist: pytest; extra == "dev"
Dynamic: author
Dynamic: classifier
Dynamic: description
Dynamic: description-content-type
Dynamic: home-page
Dynamic: keywords
Dynamic: license
Dynamic: license-file
Dynamic: platform
Dynamic: provides-extra
Dynamic: requires-dist
Dynamic: requires-python
Dynamic: summary
